{
  "updatedAt": "2026-05-07T19:09:09.461Z",
  "source": "https://servers-frontend.fivem.net/api/servers/single/okz5dj",
  "trackedPlayers": 165,
  "server": {
    "EndPoint": "okz5dj",
    "Data": {
      "hostname": "INTOUCH",
      "clients": 239,
      "sv_maxclients": 247,
      "svMaxclients": 247,
      "players": [
        {
          "id": 18,
          "name": "evelson",
          "ping": 20,
          "identifiers": [
            "steam:11000010b3ffaf3",
            "discord:563021696819265538"
          ]
        },
        {
          "id": 402,
          "name": "MrZarzyKskins.army",
          "ping": 26,
          "identifiers": [
            "steam:11000010307fbb9",
            "discord:483337651106217994"
          ]
        },
        {
          "id": 74,
          "name": "kacpex",
          "ping": 19,
          "identifiers": [
            "steam:11000013f909a2c",
            "discord:454283932519759873"
          ]
        },
        {
          "id": 4,
          "name": "Filipek",
          "ping": 13,
          "identifiers": [
            "steam:110000144ffa545",
            "discord:1003743109445845095"
          ]
        },
        {
          "id": 128,
          "name": "drm",
          "ping": 30,
          "identifiers": [
            "steam:1100001149950fe",
            "discord:726510225846304842"
          ]
        },
        {
          "id": 102,
          "name": "Taran",
          "ping": 23,
          "identifiers": [
            "steam:1100001041e5c3d",
            "discord:251012258468069377"
          ]
        },
        {
          "id": 76,
          "name": "Duller",
          "ping": 16,
          "identifiers": [
            "steam:11000011c4c3637",
            "discord:912253844505911296"
          ]
        },
        {
          "id": 386,
          "name": "KoniK",
          "ping": 36,
          "identifiers": [
            "discord:676072881498751008"
          ]
        },
        {
          "id": 127,
          "name": "dsadsa CS2.ME",
          "ping": 199,
          "identifiers": [
            "steam:11000013de6f491",
            "discord:1198406729562587259"
          ]
        },
        {
          "id": 151,
          "name": "Parkurzysta",
          "ping": 69,
          "identifiers": [
            "steam:11000013a919e31",
            "discord:501014368696139786"
          ]
        },
        {
          "id": 85,
          "name": "Avi",
          "ping": 20,
          "identifiers": [
            "steam:11000010686c41b",
            "discord:267334995239108608"
          ]
        },
        {
          "id": 259,
          "name": "Galimatias",
          "ping": 20,
          "identifiers": [
            "steam:1100001468db284",
            "discord:375677924583669760"
          ]
        },
        {
          "id": 7,
          "name": "Lisekpusty12v2",
          "ping": 19,
          "identifiers": [
            "steam:11000012fdcc85f",
            "discord:529037426568724491"
          ]
        },
        {
          "id": 47,
          "name": "szibo",
          "ping": 21,
          "identifiers": [
            "steam:110000115e2f8c7",
            "discord:376833772345229315"
          ]
        },
        {
          "id": 203,
          "name": "DevilZ33",
          "ping": 52,
          "identifiers": [
            "steam:110000101216168",
            "discord:244200198379798529"
          ]
        },
        {
          "id": 143,
          "name": "jacmal",
          "ping": 13,
          "identifiers": [
            "steam:110000142adf900",
            "discord:1359898356406816838"
          ]
        },
        {
          "id": 124,
          "name": "Escobar",
          "ping": 17,
          "identifiers": [
            "steam:110000153cbd4ce",
            "discord:418097723779186699"
          ]
        },
        {
          "id": 114,
          "name": "boro",
          "ping": 47,
          "identifiers": [
            "steam:110000147ceaf45",
            "discord:683594141678174217"
          ]
        },
        {
          "id": 45,
          "name": "diiscord",
          "ping": 53,
          "identifiers": [
            "steam:11000015f0ed069",
            "discord:1095135123768361071"
          ]
        },
        {
          "id": 62,
          "name": "YOOOOO",
          "ping": 25,
          "identifiers": [
            "steam:11000014224ba33",
            "discord:684140810354294796"
          ]
        },
        {
          "id": 29,
          "name": "Paleciarz",
          "ping": 59,
          "identifiers": [
            "steam:1100001365b6e2d",
            "discord:683306239899205734"
          ]
        },
        {
          "id": 110,
          "name": "G0NZ0",
          "ping": 18,
          "identifiers": [
            "steam:11000010aae9a16",
            "discord:1008454964764491898"
          ]
        },
        {
          "id": 16,
          "name": "alcoro",
          "ping": 81,
          "identifiers": [
            "steam:11000013e485011",
            "discord:548127720853471234"
          ]
        },
        {
          "id": 206,
          "name": "dovsky",
          "ping": 32,
          "identifiers": [
            "steam:110000119dfbf67",
            "discord:464856927952830464"
          ]
        },
        {
          "id": 169,
          "name": "ShizeR",
          "ping": 51,
          "identifiers": [
            "steam:1100001098ef151",
            "discord:343482778060587018"
          ]
        },
        {
          "id": 382,
          "name": "jvleczka",
          "ping": 43,
          "identifiers": [
            "steam:11000010a59b711",
            "discord:722022639673016320"
          ]
        },
        {
          "id": 290,
          "name": "ASDHAUF",
          "ping": 29,
          "identifiers": [
            "discord:546975154744328193"
          ]
        },
        {
          "id": 54,
          "name": "martin oppalnik",
          "ping": 13,
          "identifiers": [
            "steam:1100001151307ba",
            "discord:681236929148485694"
          ]
        },
        {
          "id": 344,
          "name": "saksofon",
          "ping": 21,
          "identifiers": [
            "discord:820426296773312552"
          ]
        },
        {
          "id": 387,
          "name": "Termi",
          "ping": 65,
          "identifiers": [
            "steam:11000013cb261e2",
            "discord:659817358801633281"
          ]
        },
        {
          "id": 229,
          "name": "SkarGrov",
          "ping": 18,
          "identifiers": [
            "steam:11000010429a07a",
            "discord:212936215316529152"
          ]
        },
        {
          "id": 161,
          "name": "mefetka",
          "ping": 30,
          "identifiers": [
            "steam:1100001665c1f00",
            "discord:942094946108842014"
          ]
        },
        {
          "id": 112,
          "name": "IraQ",
          "ping": 19,
          "identifiers": [
            "steam:1100001026a6d32",
            "discord:346627295957483521"
          ]
        },
        {
          "id": 180,
          "name": "Bary",
          "ping": 23,
          "identifiers": [
            "steam:11000010fef43cc",
            "discord:676429614259765284"
          ]
        },
        {
          "id": 186,
          "name": "AA",
          "ping": 36,
          "identifiers": [
            "steam:11000014425e13a",
            "discord:766749298729549836"
          ]
        },
        {
          "id": 329,
          "name": "Dairou",
          "ping": 56,
          "identifiers": [
            "steam:1100001072a1e82",
            "discord:1218694113164263495"
          ]
        },
        {
          "id": 264,
          "name": "sweet",
          "ping": 10,
          "identifiers": [
            "steam:11000010a7147f0",
            "discord:468524174009303060"
          ]
        },
        {
          "id": 208,
          "name": "Ini",
          "ping": 31,
          "identifiers": [
            "steam:11000010391f75b",
            "discord:174172760551981056"
          ]
        },
        {
          "id": 307,
          "name": "POPA SHURDA",
          "ping": 19,
          "identifiers": [
            "steam:1100001459fb5a1",
            "discord:415994728543158278"
          ]
        },
        {
          "id": 222,
          "name": "Mac",
          "ping": 47,
          "identifiers": [
            "steam:110000102c1ba7e",
            "discord:858402603436081202"
          ]
        },
        {
          "id": 230,
          "name": "Ustaw swoja nazwe profilu",
          "ping": 21,
          "identifiers": [
            "steam:110000142f7f1c1",
            "discord:745050170827341904"
          ]
        },
        {
          "id": 242,
          "name": "Suvex",
          "ping": 18,
          "identifiers": [
            "discord:1465813575686819922"
          ]
        },
        {
          "id": 279,
          "name": "Zabcia",
          "ping": 41,
          "identifiers": [
            "steam:110000117cfeddf",
            "discord:400674530739224576"
          ]
        },
        {
          "id": 438,
          "name": "Wicia ",
          "ping": 42,
          "identifiers": [
            "steam:110000134514905",
            "discord:451037303956176907"
          ]
        },
        {
          "id": 257,
          "name": "Antonio",
          "ping": 29,
          "identifiers": [
            "steam:11000014d32eb0f",
            "discord:372300792629035008"
          ]
        },
        {
          "id": 355,
          "name": "Dollie",
          "ping": 20,
          "identifiers": [
            "steam:110000107060a65",
            "discord:381740166227689482"
          ]
        },
        {
          "id": 283,
          "name": "KomandorFox",
          "ping": 39,
          "identifiers": [
            "steam:11000014b5e40c2",
            "discord:377163637376417794"
          ]
        },
        {
          "id": 273,
          "name": "Afghanistan",
          "ping": 23,
          "identifiers": [
            "steam:1100001417f91c9",
            "discord:780470409194897459"
          ]
        },
        {
          "id": 284,
          "name": "qwerty",
          "ping": 18,
          "identifiers": [
            "steam:1100001176c7fb1",
            "discord:416520362604625942"
          ]
        },
        {
          "id": 295,
          "name": "Hui Penk",
          "ping": 145,
          "identifiers": [
            "steam:110000115177d2d",
            "discord:390570436175593473"
          ]
        },
        {
          "id": 300,
          "name": "Grzechu",
          "ping": 55,
          "identifiers": [
            "steam:1100001420003a1",
            "discord:670614459978612756"
          ]
        },
        {
          "id": 319,
          "name": "BeBe",
          "ping": 48,
          "identifiers": [
            "steam:110000133c6bcaa",
            "discord:352541978698973186"
          ]
        },
        {
          "id": 341,
          "name": "LUKASZITO",
          "ping": 15,
          "identifiers": [
            "steam:11000010e68c03f",
            "discord:303451749463883776"
          ]
        },
        {
          "id": 361,
          "name": "zzzzzz",
          "ping": 31,
          "identifiers": [
            "steam:11000013e097026",
            "discord:241973152073252864"
          ]
        },
        {
          "id": 353,
          "name": "Pamela Anderson",
          "ping": 22,
          "identifiers": [
            "steam:110000114faf13f",
            "discord:442279585866842114"
          ]
        },
        {
          "id": 394,
          "name": "Apap Noc",
          "ping": 27,
          "identifiers": [
            "steam:110000104f5e0e6",
            "discord:247397320692465665"
          ]
        },
        {
          "id": 426,
          "name": "dominikxoxo",
          "ping": 11,
          "identifiers": [
            "steam:110000135f2944e",
            "discord:467223079760691200"
          ]
        },
        {
          "id": 432,
          "name": "zaza",
          "ping": 51,
          "identifiers": [
            "steam:11000013ec15c37",
            "discord:1433512539068567696"
          ]
        }
      ]
    }
  }
}
